aio_process_pool/__about__.py
aio_process_pool/__init__.py
aio_process_pool/executor.py
aio_process_pool/process_pool.py
aio_process_pool/utils.py
aio_process_pool/worker.py
aio_process_pool-0.1.0.dist-info/METADATA
aio_process_pool-0.1.0.dist-info/WHEEL
aio_process_pool-0.1.0.dist-info/licenses/LICENSE.txt
aio_process_pool-0.1.0.dist-info/RECORD
