Metadata-Version: 2.4
Name: aio_process_pool
Version: 0.1.0
Summary: A simple async, android compatible(, atm not thread safe) process pool implementation including a (mostly) `concurrent.futures.Executor` / `concurrent.futures.ProcessPoolExecutor` compliant `Executor`.
Project-URL: Documentation, https://github.com/jeff-dh/aio_process_pool#readme
Project-URL: Issues, https://github.com/jeff-dh/aio_process_pool/issues
Project-URL: Source, https://github.com/jeff-dh/aio_process_pool
Author-email: jeff-dh <1105041+jeff-dh@users.noreply.github.com>
License-Expression: MIT
License-File: LICENSE.txt
Classifier: Development Status :: 4 - Beta
Classifier: Programming Language :: Python
Classifier: Programming Language :: Python :: 3.8
Classifier: Programming Language :: Python :: 3.9
Classifier: Programming Language :: Python :: 3.10
Classifier: Programming Language :: Python :: 3.11
Classifier: Programming Language :: Python :: 3.12
Classifier: Programming Language :: Python :: Implementation :: CPython
Classifier: Programming Language :: Python :: Implementation :: PyPy
Requires-Python: >=3.8
